pyfigtree/__init__.py
pyfigtree/pyfigtree.py
pyfigtree/lib/libann_figtree_version.so
pyfigtree/lib/libfigtree.so
pyfigtree-1.0.1.dist-info/LICENSE
pyfigtree-1.0.1.dist-info/METADATA
pyfigtree-1.0.1.dist-info/WHEEL
pyfigtree-1.0.1.dist-info/top_level.txt
pyfigtree-1.0.1.dist-info/RECORD
