Metadata-Version: 2.1
Name: pyfigtree
Version: 1.0.1
Summary: Python ctypes wrapper of the figtree library for fast Gaussian summation
Home-page: https://github.com/fredRos/pyfigtree
Author: Frederik Beaujean
Author-email: Frederik.Beaujean@lmu.de
License-File: LICENSE
Requires-Dist: numpy
